{"Description":{"PLOT_PSTN":"대지위치","BDAR":"건축면적(㎡)","GFA":"연면적(㎡)","FART_CMPTTN_GFA":"용적률산정연면적(㎡)","FART":"용적률(%)","MN_USG_CD":"주용도코드","MN_USG_CD_NM":"주용도코드명","ETC_USG":"기타용도"},"Data":[{"PLOT_PSTN":"서울특별시 노원구 중계동 3번지","BDAR":260.53,"GFA":422.59,"FART_CMPTTN_GFA":260.53,"FART":12.94,"MN_USG_CD":"04000","MN_USG_CD_NM":"제2종근린생활시설","ETC_USG":"제2종근린생활시설(사찰)"},{"PLOT_PSTN":"서울특별시 노원구 중계동 21-49번지","BDAR":122.68,"GFA":122.68,"FART_CMPTTN_GFA":122.68,"FART":0,"MN_USG_CD":"01000","MN_USG_CD_NM":"단독주택","ETC_USG":"주택"},{"PLOT_PSTN":"서울특별시 노원구 중계동 21-50번지","BDAR":66.68,"GFA":66.68,"FART_CMPTTN_GFA":66.68,"FART":0,"MN_USG_CD":"01000","MN_USG_CD_NM":"단독주택","ETC_USG":"단독주택"},{"PLOT_PSTN":"서울특별시 노원구 중계동 21-52번지","BDAR":134.86,"GFA":134.86,"FART_CMPTTN_GFA":134.86,"FART":0,"MN_USG_CD":"01000","MN_USG_CD_NM":"단독주택","ETC_USG":"주택"},{"PLOT_PSTN":"서울특별시 노원구 중계동 21-53번지","BDAR":126.59,"GFA":126.59,"FART_CMPTTN_GFA":126.59,"FART":0,"MN_USG_CD":"01000","MN_USG_CD_NM":"단독주택","ETC_USG":"주택"},{"PLOT_PSTN":"서울특별시 노원구 중계동 21-54번지","BDAR":99.78,"GFA":99.78,"FART_CMPTTN_GFA":99.78,"FART":0,"MN_USG_CD":"01000","MN_USG_CD_NM":"단독주택","ETC_USG":"주택"},{"PLOT_PSTN":"서울특별시 노원구 중계동 21-55번지","BDAR":81.37,"GFA":81.37,"FART_CMPTTN_GFA":81.37,"FART":0,"MN_USG_CD":"01000","MN_USG_CD_NM":"단독주택","ETC_USG":"주택"},{"PLOT_PSTN":"서울특별시 노원구 중계동 24-8번지","BDAR":73.88,"GFA":73.88,"FART_CMPTTN_GFA":73.88,"FART":0,"MN_USG_CD":"01000","MN_USG_CD_NM":"단독주택","ETC_USG":"주택"},{"PLOT_PSTN":"서울특별시 노원구 중계동 24-14번지","BDAR":85.5,"GFA":85.5,"FART_CMPTTN_GFA":85.5,"FART":0,"MN_USG_CD":"01000","MN_USG_CD_NM":"단독주택","ETC_USG":"주택"},{"PLOT_PSTN":"서울특별시 노원구 중계동 24-15번지","BDAR":75,"GFA":75,"FART_CMPTTN_GFA":75,"FART":0,"MN_USG_CD":"01000","MN_USG_CD_NM":"단독주택","ETC_USG":"주택"},{"PLOT_PSTN":"서울특별시 노원구 중계동 24-18번지","BDAR":84,"GFA":84,"FART_CMPTTN_GFA":84,"FART":0,"MN_USG_CD":"01000","MN_USG_CD_NM":"단독주택","ETC_USG":"주택"},{"PLOT_PSTN":"서울특별시 노원구 중계동 24-19번지","BDAR":75,"GFA":75,"FART_CMPTTN_GFA":75,"FART":0,"MN_USG_CD":"01000","MN_USG_CD_NM":"단독주택","ETC_USG":"주택"},{"PLOT_PSTN":"서울특별시 노원구 중계동 24-20번지","BDAR":88.7,"GFA":88.7,"FART_CMPTTN_GFA":88.7,"FART":0,"MN_USG_CD":"01000","MN_USG_CD_NM":"단독주택","ETC_USG":"주택"},{"PLOT_PSTN":"서울특별시 노원구 중계동 24-23번지","BDAR":55.35,"GFA":55.35,"FART_CMPTTN_GFA":55.35,"FART":0,"MN_USG_CD":"01000","MN_USG_CD_NM":"단독주택","ETC_USG":"주택"},{"PLOT_PSTN":"서울특별시 노원구 중계동 24-25번지","BDAR":40,"GFA":40,"FART_CMPTTN_GFA":40,"FART":0,"MN_USG_CD":"01000","MN_USG_CD_NM":"단독주택","ETC_USG":"주택"},{"PLOT_PSTN":"서울특별시 노원구 중계동 24-27번지","BDAR":37.25,"GFA":37.25,"FART_CMPTTN_GFA":37.25,"FART":0,"MN_USG_CD":"01000","MN_USG_CD_NM":"단독주택","ETC_USG":"주택"},{"PLOT_PSTN":"서울특별시 노원구 중계동 24-28번지","BDAR":88,"GFA":88,"FART_CMPTTN_GFA":88,"FART":0,"MN_USG_CD":"01000","MN_USG_CD_NM":"단독주택","ETC_USG":"주택"},{"PLOT_PSTN":"서울특별시 노원구 중계동 24-31번지","BDAR":107,"GFA":147,"FART_CMPTTN_GFA":147,"FART":0,"MN_USG_CD":"01000","MN_USG_CD_NM":"단독주택","ETC_USG":"주택"},{"PLOT_PSTN":"서울특별시 노원구 중계동 24-32번지","BDAR":43.75,"GFA":43.75,"FART_CMPTTN_GFA":43.75,"FART":0,"MN_USG_CD":"01000","MN_USG_CD_NM":"단독주택","ETC_USG":"주택"},{"PLOT_PSTN":"서울특별시 노원구 중계동 24-34번지","BDAR":99,"GFA":99,"FART_CMPTTN_GFA":99,"FART":0,"MN_USG_CD":"01000","MN_USG_CD_NM":"단독주택","ETC_USG":"주택"},{"PLOT_PSTN":"서울특별시 노원구 중계동 24-35번지","BDAR":82.88,"GFA":82.88,"FART_CMPTTN_GFA":82.88,"FART":0,"MN_USG_CD":"01000","MN_USG_CD_NM":"단독주택","ETC_USG":"주택"},{"PLOT_PSTN":"서울특별시 노원구 중계동 25-1번지","BDAR":115,"GFA":115,"FART_CMPTTN_GFA":115,"FART":0,"MN_USG_CD":"01000","MN_USG_CD_NM":"단독주택","ETC_USG":"주택,근린생활시설"},{"PLOT_PSTN":"서울특별시 노원구 중계동 25-2번지","BDAR":48,"GFA":48,"FART_CMPTTN_GFA":48,"FART":0,"MN_USG_CD":"01000","MN_USG_CD_NM":"단독주택","ETC_USG":"주택"},{"PLOT_PSTN":"서울특별시 노원구 중계동 25-3번지","BDAR":97.75,"GFA":97.75,"FART_CMPTTN_GFA":97.75,"FART":0,"MN_USG_CD":"01000","MN_USG_CD_NM":"단독주택","ETC_USG":"주택"},{"PLOT_PSTN":"서울특별시 노원구 중계동 25-5번지","BDAR":66.5,"GFA":66.5,"FART_CMPTTN_GFA":66.5,"FART":0,"MN_USG_CD":"01000","MN_USG_CD_NM":"단독주택","ETC_USG":"주택"},{"PLOT_PSTN":"서울특별시 노원구 중계동 25-7번지","BDAR":56.76,"GFA":56.76,"FART_CMPTTN_GFA":56.76,"FART":0,"MN_USG_CD":"01000","MN_USG_CD_NM":"단독주택","ETC_USG":"주택"},{"PLOT_PSTN":"서울특별시 노원구 중계동 25-10번지","BDAR":52.5,"GFA":52.5,"FART_CMPTTN_GFA":52.5,"FART":0,"MN_USG_CD":"01000","MN_USG_CD_NM":"단독주택","ETC_USG":"주택"},{"PLOT_PSTN":"서울특별시 노원구 중계동 25-11번지","BDAR":56,"GFA":56,"FART_CMPTTN_GFA":56,"FART":0,"MN_USG_CD":"01000","MN_USG_CD_NM":"단독주택","ETC_USG":"주택"},{"PLOT_PSTN":"서울특별시 노원구 중계동 25-12번지","BDAR":73,"GFA":73,"FART_CMPTTN_GFA":73,"FART":0,"MN_USG_CD":"01000","MN_USG_CD_NM":"단독주택","ETC_USG":"주택"},{"PLOT_PSTN":"서울특별시 노원구 중계동 28-7번지","BDAR":75,"GFA":75,"FART_CMPTTN_GFA":75,"FART":0,"MN_USG_CD":"01000","MN_USG_CD_NM":"단독주택","ETC_USG":"주택"},{"PLOT_PSTN":"서울특별시 노원구 중계동 28-9번지","BDAR":94.85,"GFA":94.85,"FART_CMPTTN_GFA":94.85,"FART":0,"MN_USG_CD":"01000","MN_USG_CD_NM":"단독주택","ETC_USG":"주택"},{"PLOT_PSTN":"서울특별시 노원구 중계동 28-10번지","BDAR":101,"GFA":101,"FART_CMPTTN_GFA":101,"FART":0,"MN_USG_CD":"01000","MN_USG_CD_NM":"단독주택","ETC_USG":"주택,근린생활시설"},{"PLOT_PSTN":"서울특별시 노원구 중계동 28-11번지","BDAR":115,"GFA":115,"FART_CMPTTN_GFA":115,"FART":0,"MN_USG_CD":"01000","MN_USG_CD_NM":"단독주택","ETC_USG":"주택,근린생활시설"},{"PLOT_PSTN":"서울특별시 노원구 중계동 28-12번지","BDAR":117.5,"GFA":117.5,"FART_CMPTTN_GFA":117.5,"FART":0,"MN_USG_CD":"01000","MN_USG_CD_NM":"단독주택","ETC_USG":"주택,근린생활시설"},{"PLOT_PSTN":"서울특별시 노원구 중계동 28-14번지","BDAR":57,"GFA":57,"FART_CMPTTN_GFA":57,"FART":0,"MN_USG_CD":"01000","MN_USG_CD_NM":"단독주택","ETC_USG":"주택"},{"PLOT_PSTN":"서울특별시 노원구 중계동 29-3번지","BDAR":71.5,"GFA":71.5,"FART_CMPTTN_GFA":71.5,"FART":0,"MN_USG_CD":"01000","MN_USG_CD_NM":"단독주택","ETC_USG":"주택"},{"PLOT_PSTN":"서울특별시 노원구 중계동 29-6번지","BDAR":76.77,"GFA":76.77,"FART_CMPTTN_GFA":76.77,"FART":0,"MN_USG_CD":"01000","MN_USG_CD_NM":"단독주택","ETC_USG":"주택"},{"PLOT_PSTN":"서울특별시 노원구 중계동 29-14번지","BDAR":91.34,"GFA":91.34,"FART_CMPTTN_GFA":91.34,"FART":0,"MN_USG_CD":"01000","MN_USG_CD_NM":"단독주택","ETC_USG":"주택"},{"PLOT_PSTN":"서울특별시 노원구 중계동 29-15번지","BDAR":71.27,"GFA":71.27,"FART_CMPTTN_GFA":71.27,"FART":0,"MN_USG_CD":"01000","MN_USG_CD_NM":"단독주택","ETC_USG":"주택"},{"PLOT_PSTN":"서울특별시 노원구 중계동 29-16번지","BDAR":108.54,"GFA":108.54,"FART_CMPTTN_GFA":108.54,"FART":0,"MN_USG_CD":"01000","MN_USG_CD_NM":"단독주택","ETC_USG":"주택"},{"PLOT_PSTN":"서울특별시 노원구 중계동 29-20번지","BDAR":111.92,"GFA":111.92,"FART_CMPTTN_GFA":111.92,"FART":0,"MN_USG_CD":"01000","MN_USG_CD_NM":"단독주택","ETC_USG":"주택"},{"PLOT_PSTN":"서울특별시 노원구 중계동 29-23번지","BDAR":75.3,"GFA":85.3,"FART_CMPTTN_GFA":75.3,"FART":0,"MN_USG_CD":"01000","MN_USG_CD_NM":"단독주택","ETC_USG":"주택"},{"PLOT_PSTN":"서울특별시 노원구 중계동 29-24번지","BDAR":70,"GFA":70,"FART_CMPTTN_GFA":70,"FART":0,"MN_USG_CD":"01000","MN_USG_CD_NM":"단독주택","ETC_USG":"주택"},{"PLOT_PSTN":"서울특별시 노원구 중계동 29-25번지","BDAR":63.5,"GFA":63.5,"FART_CMPTTN_GFA":63.5,"FART":0,"MN_USG_CD":"01000","MN_USG_CD_NM":"단독주택","ETC_USG":"주택"},{"PLOT_PSTN":"서울특별시 노원구 중계동 29-28번지","BDAR":76.14,"GFA":76.14,"FART_CMPTTN_GFA":76.14,"FART":0,"MN_USG_CD":"01000","MN_USG_CD_NM":"단독주택","ETC_USG":"주택"},{"PLOT_PSTN":"서울특별시 노원구 중계동 29-31번지","BDAR":91.96,"GFA":91.96,"FART_CMPTTN_GFA":91.96,"FART":0,"MN_USG_CD":"01000","MN_USG_CD_NM":"단독주택","ETC_USG":"주택"},{"PLOT_PSTN":"서울특별시 노원구 중계동 29-32번지","BDAR":94.53,"GFA":94.53,"FART_CMPTTN_GFA":94.53,"FART":0,"MN_USG_CD":"01000","MN_USG_CD_NM":"단독주택","ETC_USG":"주택"},{"PLOT_PSTN":"서울특별시 노원구 중계동 29-33번지","BDAR":112.27,"GFA":112.27,"FART_CMPTTN_GFA":112.27,"FART":0,"MN_USG_CD":"01000","MN_USG_CD_NM":"단독주택","ETC_USG":"주택"},{"PLOT_PSTN":"서울특별시 노원구 중계동 29-34번지","BDAR":109.41,"GFA":109.41,"FART_CMPTTN_GFA":109.41,"FART":0,"MN_USG_CD":"01000","MN_USG_CD_NM":"단독주택","ETC_USG":"주택"},{"PLOT_PSTN":"서울특별시 노원구 중계동 29-37번지","BDAR":83.19,"GFA":83.19,"FART_CMPTTN_GFA":83.19,"FART":0,"MN_USG_CD":"01000","MN_USG_CD_NM":"단독주택","ETC_USG":"주택"},{"PLOT_PSTN":"서울특별시 노원구 중계동 29-38번지","BDAR":122.26,"GFA":122.26,"FART_CMPTTN_GFA":122.26,"FART":0,"MN_USG_CD":"01000","MN_USG_CD_NM":"단독주택","ETC_USG":"주택"},{"PLOT_PSTN":"서울특별시 노원구 중계동 29-39번지","BDAR":79.33,"GFA":79.33,"FART_CMPTTN_GFA":79.33,"FART":0,"MN_USG_CD":"01000","MN_USG_CD_NM":"단독주택","ETC_USG":"주택"},{"PLOT_PSTN":"서울특별시 노원구 중계동 29-40번지","BDAR":69.07,"GFA":69.07,"FART_CMPTTN_GFA":69.07,"FART":0,"MN_USG_CD":"01000","MN_USG_CD_NM":"단독주택","ETC_USG":"주택"},{"PLOT_PSTN":"서울특별시 노원구 중계동 29-47번지","BDAR":118.27,"GFA":118.27,"FART_CMPTTN_GFA":118.27,"FART":0,"MN_USG_CD":"01000","MN_USG_CD_NM":"단독주택","ETC_USG":"주택,근린생활시설"},{"PLOT_PSTN":"서울특별시 노원구 중계동 30번지","BDAR":233.83,"GFA":233.83,"FART_CMPTTN_GFA":233.83,"FART":45.67,"MN_USG_CD":"04000","MN_USG_CD_NM":"제2종근린생활시설","ETC_USG":"제2종근린생활시설(교회)"},{"PLOT_PSTN":"서울특별시 노원구 중계동 30-4번지","BDAR":158.25,"GFA":158.25,"FART_CMPTTN_GFA":158.25,"FART":0,"MN_USG_CD":"01000","MN_USG_CD_NM":"단독주택","ETC_USG":"주택,근린생활시설"},{"PLOT_PSTN":"서울특별시 노원구 중계동 30-7번지","BDAR":66.61,"GFA":66.61,"FART_CMPTTN_GFA":66.61,"FART":0,"MN_USG_CD":"01000","MN_USG_CD_NM":"단독주택","ETC_USG":"주택"},{"PLOT_PSTN":"서울특별시 노원구 중계동 30-8번지","BDAR":65,"GFA":65,"FART_CMPTTN_GFA":65,"FART":0,"MN_USG_CD":"01000","MN_USG_CD_NM":"단독주택","ETC_USG":"주택"},{"PLOT_PSTN":"서울특별시 노원구 중계동 30-9번지","BDAR":97.7,"GFA":97.7,"FART_CMPTTN_GFA":97.7,"FART":0,"MN_USG_CD":"01000","MN_USG_CD_NM":"단독주택","ETC_USG":"주택"},{"PLOT_PSTN":"서울특별시 노원구 중계동 30-10번지","BDAR":65.5,"GFA":65.5,"FART_CMPTTN_GFA":65.5,"FART":0,"MN_USG_CD":"01000","MN_USG_CD_NM":"단독주택","ETC_USG":"주택"},{"PLOT_PSTN":"서울특별시 노원구 중계동 30-11번지","BDAR":84.48,"GFA":84.48,"FART_CMPTTN_GFA":84.48,"FART":0,"MN_USG_CD":"01000","MN_USG_CD_NM":"단독주택","ETC_USG":"주택"},{"PLOT_PSTN":"서울특별시 노원구 중계동 30-12번지","BDAR":67.08,"GFA":67.08,"FART_CMPTTN_GFA":67.08,"FART":0,"MN_USG_CD":"01000","MN_USG_CD_NM":"단독주택","ETC_USG":"주택"},{"PLOT_PSTN":"서울특별시 노원구 중계동 30-13번지","BDAR":85.5,"GFA":85.5,"FART_CMPTTN_GFA":85.5,"FART":0,"MN_USG_CD":"01000","MN_USG_CD_NM":"단독주택","ETC_USG":"주택"},{"PLOT_PSTN":"서울특별시 노원구 중계동 30-14번지","BDAR":68,"GFA":68,"FART_CMPTTN_GFA":68,"FART":0,"MN_USG_CD":"01000","MN_USG_CD_NM":"단독주택","ETC_USG":"주택,근린생활시설"},{"PLOT_PSTN":"서울특별시 노원구 중계동 30-15번지","BDAR":72.92,"GFA":72.92,"FART_CMPTTN_GFA":72.92,"FART":0,"MN_USG_CD":"01000","MN_USG_CD_NM":"단독주택","ETC_USG":"주택"},{"PLOT_PSTN":"서울특별시 노원구 중계동 30-29번지","BDAR":160.25,"GFA":160.25,"FART_CMPTTN_GFA":160.25,"FART":0,"MN_USG_CD":"01000","MN_USG_CD_NM":"단독주택","ETC_USG":"주택"},{"PLOT_PSTN":"서울특별시 노원구 중계동 30-30번지","BDAR":121.7,"GFA":121.7,"FART_CMPTTN_GFA":121.7,"FART":0,"MN_USG_CD":"01000","MN_USG_CD_NM":"단독주택","ETC_USG":"주택"},{"PLOT_PSTN":"서울특별시 노원구 중계동 30-31번지","BDAR":104.66,"GFA":104.66,"FART_CMPTTN_GFA":104.66,"FART":0,"MN_USG_CD":"01000","MN_USG_CD_NM":"단독주택","ETC_USG":"주택"},{"PLOT_PSTN":"서울특별시 노원구 중계동 31-1번지","BDAR":218.67,"GFA":656.01,"FART_CMPTTN_GFA":437.34,"FART":0,"MN_USG_CD":"02000","MN_USG_CD_NM":"공동주택","ETC_USG":"다세대주택"},{"PLOT_PSTN":"서울특별시 노원구 중계동 34-5번지","BDAR":4056.59,"GFA":66484.81,"FART_CMPTTN_GFA":47092.47,"FART":285.13,"MN_USG_CD":"02000","MN_USG_CD_NM":"공동주택","ETC_USG":"공동주택(아파트)"},{"PLOT_PSTN":"서울특별시 노원구 중계동 37번지","BDAR":575.21,"GFA":535.54,"FART_CMPTTN_GFA":575.21,"FART":0,"MN_USG_CD":"01000","MN_USG_CD_NM":"단독주택","ETC_USG":"주택"},{"PLOT_PSTN":"서울특별시 노원구 중계동 38번지","BDAR":403.34,"GFA":403.34,"FART_CMPTTN_GFA":403.34,"FART":0,"MN_USG_CD":"01000","MN_USG_CD_NM":"단독주택","ETC_USG":"주택,근린생활시설"},{"PLOT_PSTN":"서울특별시 노원구 중계동 40번지","BDAR":152.07,"GFA":152.07,"FART_CMPTTN_GFA":152.07,"FART":0,"MN_USG_CD":"01000","MN_USG_CD_NM":"단독주택","ETC_USG":"주택"},{"PLOT_PSTN":"서울특별시 노원구 중계동 49번지","BDAR":4761.24,"GFA":32097.87,"FART_CMPTTN_GFA":26948.24,"FART":197.73,"MN_USG_CD":"02000","MN_USG_CD_NM":"공동주택","ETC_USG":"아파트"},{"PLOT_PSTN":"서울특별시 노원구 중계동 67번지","BDAR":3610.12,"GFA":10627.03,"FART_CMPTTN_GFA":10197.05,"FART":76.21,"MN_USG_CD":"10000","MN_USG_CD_NM":"교육연구시설","ETC_USG":"교육연구시설"},{"PLOT_PSTN":"서울특별시 노원구 중계동 69번지","BDAR":379.21,"GFA":1887.41,"FART_CMPTTN_GFA":1763.72,"FART":235.16,"MN_USG_CD":"04000","MN_USG_CD_NM":"제2종근린생활시설","ETC_USG":"제2종근린생활시설"},{"PLOT_PSTN":"서울특별시 노원구 중계동 75번지","BDAR":158.69,"GFA":158.69,"FART_CMPTTN_GFA":158.69,"FART":0,"MN_USG_CD":"01000","MN_USG_CD_NM":"단독주택","ETC_USG":"주택"},{"PLOT_PSTN":"서울특별시 노원구 중계동 75-4번지","BDAR":337.81,"GFA":1287.43,"FART_CMPTTN_GFA":1287.43,"FART":199.91,"MN_USG_CD":"02000","MN_USG_CD_NM":"공동주택","ETC_USG":"공동주택(도시형생활주택)"},{"PLOT_PSTN":"서울특별시 노원구 중계동 78번지","BDAR":1680.12,"GFA":20249.76,"FART_CMPTTN_GFA":18384.12,"FART":0,"MN_USG_CD":"02000","MN_USG_CD_NM":"공동주택","ETC_USG":"아파트,상가"},{"PLOT_PSTN":"서울특별시 노원구 중계동 84-3번지","BDAR":230.36,"GFA":941.18,"FART_CMPTTN_GFA":753.44,"FART":152.21,"MN_USG_CD":"02000","MN_USG_CD_NM":"공동주택","ETC_USG":"다세대주택"},{"PLOT_PSTN":"서울특별시 노원구 중계동 90번지","BDAR":350.42,"GFA":350.42,"FART_CMPTTN_GFA":350.42,"FART":0,"MN_USG_CD":"01000","MN_USG_CD_NM":"단독주택","ETC_USG":"주택"},{"PLOT_PSTN":"서울특별시 노원구 중계동 90-9번지","BDAR":158,"GFA":158,"FART_CMPTTN_GFA":104.68,"FART":0,"MN_USG_CD":"01000","MN_USG_CD_NM":"단독주택","ETC_USG":"주택"},{"PLOT_PSTN":"서울특별시 노원구 중계동 90-10번지","BDAR":187.77,"GFA":716.07,"FART_CMPTTN_GFA":659.59,"FART":0,"MN_USG_CD":"02000","MN_USG_CD_NM":"공동주택","ETC_USG":"다세대"},{"PLOT_PSTN":"서울특별시 노원구 중계동 90-24번지","BDAR":336.82,"GFA":1249.58,"FART_CMPTTN_GFA":1249.58,"FART":219.22,"MN_USG_CD":"02000","MN_USG_CD_NM":"공동주택","ETC_USG":"다세대주택"},{"PLOT_PSTN":"서울특별시 노원구 중계동 90-26번지","BDAR":276.96,"GFA":989.19,"FART_CMPTTN_GFA":739.82,"FART":114.03,"MN_USG_CD":"02000","MN_USG_CD_NM":"공동주택","ETC_USG":"다세대주택"},{"PLOT_PSTN":"서울특별시 노원구 중계동 90-43번지","BDAR":139.6,"GFA":495.14,"FART_CMPTTN_GFA":351.94,"FART":0,"MN_USG_CD":"01000","MN_USG_CD_NM":"단독주택","ETC_USG":"근린생활시설,주택"},{"PLOT_PSTN":"서울특별시 노원구 중계동 91-1번지","BDAR":335.14,"GFA":785.02,"FART_CMPTTN_GFA":651.64,"FART":55.74,"MN_USG_CD":"11000","MN_USG_CD_NM":"노유자시설","ETC_USG":"교육연구및복지시설, 주택"},{"PLOT_PSTN":"서울특별시 노원구 중계동 103번지","BDAR":1947.96,"GFA":11628.1,"FART_CMPTTN_GFA":9629.1,"FART":0,"MN_USG_CD":"02000","MN_USG_CD_NM":"공동주택","ETC_USG":"아파트"},{"PLOT_PSTN":"서울특별시 노원구 중계동 110번지","BDAR":300.3,"GFA":1016.72,"FART_CMPTTN_GFA":1016.72,"FART":199.75,"MN_USG_CD":"02000","MN_USG_CD_NM":"공동주택","ETC_USG":"공동주택(도시형생활주택)"},{"PLOT_PSTN":"서울특별시 노원구 중계동 113-1번지","BDAR":240.69,"GFA":894.52,"FART_CMPTTN_GFA":894.52,"FART":189.52,"MN_USG_CD":"02000","MN_USG_CD_NM":"공동주택","ETC_USG":"다세대주택"},{"PLOT_PSTN":"서울특별시 노원구 중계동 118번지","BDAR":5491.9,"GFA":21514.82,"FART_CMPTTN_GFA":20152.95,"FART":136.55,"MN_USG_CD":"10000","MN_USG_CD_NM":"교육연구시설","ETC_USG":"교육연구시설"},{"PLOT_PSTN":"서울특별시 노원구 중계동 129번지","BDAR":6228.07,"GFA":22105.97,"FART_CMPTTN_GFA":20626.06,"FART":65.55,"MN_USG_CD":"10000","MN_USG_CD_NM":"교육연구시설","ETC_USG":"교육연구및복지시설"},{"PLOT_PSTN":"서울특별시 노원구 중계동 130번지","BDAR":76.03,"GFA":119.01,"FART_CMPTTN_GFA":76.03,"FART":0,"MN_USG_CD":"01000","MN_USG_CD_NM":"단독주택","ETC_USG":"주택"},{"PLOT_PSTN":"서울특별시 노원구 중계동 131-4번지","BDAR":871.9,"GFA":1652,"FART_CMPTTN_GFA":1652,"FART":49.4,"MN_USG_CD":"10000","MN_USG_CD_NM":"교육연구시설","ETC_USG":"교육연구시설"},{"PLOT_PSTN":"서울특별시 노원구 중계동 132번지","BDAR":3907.58,"GFA":11847.5,"FART_CMPTTN_GFA":11403.15,"FART":56.73,"MN_USG_CD":"Z8000","MN_USG_CD_NM":"교육연구및복지시설","ETC_USG":"교육연구시설"},{"PLOT_PSTN":"서울특별시 노원구 중계동 134-1번지","BDAR":269.41,"GFA":972.42,"FART_CMPTTN_GFA":704.49,"FART":0,"MN_USG_CD":"02000","MN_USG_CD_NM":"공동주택","ETC_USG":"다세대주택"},{"PLOT_PSTN":"서울특별시 노원구 중계동 142-8번지","BDAR":237.64,"GFA":896.94,"FART_CMPTTN_GFA":896.94,"FART":188.43,"MN_USG_CD":"02000","MN_USG_CD_NM":"공동주택","ETC_USG":"도시형생활주택(단지형다세대)"},{"PLOT_PSTN":"서울특별시 노원구 중계동 161-1번지","BDAR":4290.39,"GFA":61006.02,"FART_CMPTTN_GFA":48824.29,"FART":293.38,"MN_USG_CD":"02000","MN_USG_CD_NM":"공동주택","ETC_USG":"공동주택(아파트), 생활편익시설, 의료시설"},{"PLOT_PSTN":"서울특별시 노원구 중계동 168-3번지","BDAR":332.12,"GFA":1140.62,"FART_CMPTTN_GFA":1140.62,"FART":199.76,"MN_USG_CD":"02000","MN_USG_CD_NM":"공동주택","ETC_USG":"공동주택(다세대주택)"},{"PLOT_PSTN":"서울특별시 노원구 중계동 168-8번지","BDAR":254.47,"GFA":847.2,"FART_CMPTTN_GFA":847.2,"FART":197.02,"MN_USG_CD":"02000","MN_USG_CD_NM":"공동주택","ETC_USG":null},{"PLOT_PSTN":"서울특별시 노원구 중계동 168-9번지","BDAR":254.47,"GFA":847.2,"FART_CMPTTN_GFA":847.2,"FART":197.02,"MN_USG_CD":"02000","MN_USG_CD_NM":"공동주택","ETC_USG":null},{"PLOT_PSTN":"서울특별시 노원구 중계동 168-10번지","BDAR":256.86,"GFA":865.98,"FART_CMPTTN_GFA":865.98,"FART":199.99,"MN_USG_CD":"02000","MN_USG_CD_NM":"공동주택","ETC_USG":"공동주택(다세대주택)"},{"PLOT_PSTN":"서울특별시 노원구 중계동 168-11번지","BDAR":319.38,"GFA":1136.36,"FART_CMPTTN_GFA":1136.36,"FART":212,"MN_USG_CD":"02000","MN_USG_CD_NM":"공동주택","ETC_USG":"다세대주택"},{"PLOT_PSTN":"서울특별시 노원구 중계동 201번지","BDAR":71.17,"GFA":71.17,"FART_CMPTTN_GFA":71.17,"FART":0,"MN_USG_CD":"01000","MN_USG_CD_NM":"단독주택","ETC_USG":"주택"},{"PLOT_PSTN":"서울특별시 노원구 중계동 236-3번지","BDAR":496.48,"GFA":956.02,"FART_CMPTTN_GFA":847.26,"FART":89.94,"MN_USG_CD":"03000","MN_USG_CD_NM":"제1종근린생활시설","ETC_USG":"근린생활시설, 주택"},{"PLOT_PSTN":"서울특별시 노원구 중계동 313번지","BDAR":3667.48,"GFA":18390.92,"FART_CMPTTN_GFA":13074.74,"FART":101.29,"MN_USG_CD":"10000","MN_USG_CD_NM":"교육연구시설","ETC_USG":"교육연구및복지시설"},{"PLOT_PSTN":"서울특별시 노원구 중계동 358번지","BDAR":5450.6,"GFA":64137.2,"FART_CMPTTN_GFA":56244.56,"FART":186.43,"MN_USG_CD":"02000","MN_USG_CD_NM":"공동주택","ETC_USG":"공동주택(아파트)"},{"PLOT_PSTN":"서울특별시 노원구 중계동 358-2번지","BDAR":3981.03,"GFA":58604.69,"FART_CMPTTN_GFA":54222.11,"FART":0,"MN_USG_CD":"02000","MN_USG_CD_NM":"공동주택","ETC_USG":"아파트"},{"PLOT_PSTN":"서울특별시 노원구 중계동 358-3번지","BDAR":3196.45,"GFA":9765.15,"FART_CMPTTN_GFA":9765.15,"FART":74.55,"MN_USG_CD":"10000","MN_USG_CD_NM":"교육연구시설","ETC_USG":"교육연구시설"},{"PLOT_PSTN":"서울특별시 노원구 중계동 359번지","BDAR":2974.8,"GFA":9626.06,"FART_CMPTTN_GFA":9537.26,"FART":80.83,"MN_USG_CD":"10000","MN_USG_CD_NM":"교육연구시설","ETC_USG":"교육연구시설"},{"PLOT_PSTN":"서울특별시 노원구 중계동 359-1번지","BDAR":11666.76,"GFA":176522.1,"FART_CMPTTN_GFA":164394.92,"FART":0,"MN_USG_CD":"02000","MN_USG_CD_NM":"공동주택","ETC_USG":"아파트"},{"PLOT_PSTN":"서울특별시 노원구 중계동 360-2번지","BDAR":7780.94,"GFA":110118.44,"FART_CMPTTN_GFA":84267.62,"FART":195.45,"MN_USG_CD":"02000","MN_USG_CD_NM":"공동주택","ETC_USG":"아파트,부대복리시설"},{"PLOT_PSTN":"서울특별시 노원구 중계동 360-15번지","BDAR":10176.01,"GFA":121874.98,"FART_CMPTTN_GFA":99213.34,"FART":217.1,"MN_USG_CD":"02000","MN_USG_CD_NM":"공동주택","ETC_USG":"공동주택(아파트)"},{"PLOT_PSTN":"서울특별시 노원구 중계동 360-16번지","BDAR":2542.26,"GFA":26774.1,"FART_CMPTTN_GFA":24102.39,"FART":206.44,"MN_USG_CD":"02000","MN_USG_CD_NM":"공동주택","ETC_USG":"아파트"},{"PLOT_PSTN":"서울특별시 노원구 중계동 361-1번지","BDAR":6725.765,"GFA":95848.65,"FART_CMPTTN_GFA":73675.21,"FART":208.3,"MN_USG_CD":"02000","MN_USG_CD_NM":"공동주택","ETC_USG":"아파트,근린생활시설,의료시설,교육연구및복지시설"},{"PLOT_PSTN":"서울특별시 노원구 중계동 362-1번지","BDAR":3339.9,"GFA":50364.75,"FART_CMPTTN_GFA":46409.22,"FART":0,"MN_USG_CD":"02000","MN_USG_CD_NM":"공동주택","ETC_USG":"아파트"},{"PLOT_PSTN":"서울특별시 노원구 중계동 363번지","BDAR":4485.93,"GFA":70675.66,"FART_CMPTTN_GFA":56863.71,"FART":0,"MN_USG_CD":"02000","MN_USG_CD_NM":"공동주택","ETC_USG":"아파트,구매시설,생활시설,의료시설"},{"PLOT_PSTN":"서울특별시 노원구 중계동 363-1번지","BDAR":3357.47,"GFA":39192.17,"FART_CMPTTN_GFA":36792.55,"FART":0,"MN_USG_CD":"02000","MN_USG_CD_NM":"공동주택","ETC_USG":"아파트"},{"PLOT_PSTN":"서울특별시 노원구 중계동 363-7번지","BDAR":651.5,"GFA":1801.95,"FART_CMPTTN_GFA":1278.81,"FART":70.76,"MN_USG_CD":"11000","MN_USG_CD_NM":"노유자시설","ETC_USG":"노유자시설(아동복지시설)"},{"PLOT_PSTN":"서울특별시 노원구 중계동 364번지","BDAR":5592.53,"GFA":77735.44,"FART_CMPTTN_GFA":63896.62,"FART":217.19,"MN_USG_CD":"02000","MN_USG_CD_NM":"공동주택","ETC_USG":"아파트,구매시설,생활시설"},{"PLOT_PSTN":"서울특별시 노원구 중계동 364-12번지","BDAR":2367,"GFA":37315,"FART_CMPTTN_GFA":34394.52,"FART":0,"MN_USG_CD":"02000","MN_USG_CD_NM":"공동주택","ETC_USG":"아파트"},{"PLOT_PSTN":"서울특별시 노원구 중계동 366번지","BDAR":10997.06,"GFA":152135.11,"FART_CMPTTN_GFA":122986.85,"FART":0,"MN_USG_CD":"02000","MN_USG_CD_NM":"공동주택","ETC_USG":"아파트,구매시설,생활시설,의료시설"},{"PLOT_PSTN":"서울특별시 노원구 중계동 369번지","BDAR":7281.11,"GFA":108213.12,"FART_CMPTTN_GFA":100279.1,"FART":0,"MN_USG_CD":"02000","MN_USG_CD_NM":"공동주택","ETC_USG":"아파트"},{"PLOT_PSTN":"서울특별시 노원구 중계동 369-3번지","BDAR":3847.41,"GFA":13224.56,"FART_CMPTTN_GFA":13224.56,"FART":97.02,"MN_USG_CD":"10000","MN_USG_CD_NM":"교육연구시설","ETC_USG":"교육연구시설"},{"PLOT_PSTN":"서울특별시 노원구 중계동 409번지","BDAR":1726.82,"GFA":8826.86,"FART_CMPTTN_GFA":7260.23,"FART":59.7,"MN_USG_CD":"Z8000","MN_USG_CD_NM":"교육연구및복지시설","ETC_USG":"교육연구및복지시설(고등기술학교)"},{"PLOT_PSTN":"서울특별시 노원구 중계동 421-1번지","BDAR":26,"GFA":62.88,"FART_CMPTTN_GFA":26,"FART":0,"MN_USG_CD":"03000","MN_USG_CD_NM":"제1종근린생활시설","ETC_USG":"주택,근린생활시설"},{"PLOT_PSTN":"서울특별시 노원구 중계동 435-1번지","BDAR":2218.49,"GFA":33705.8,"FART_CMPTTN_GFA":29343.29,"FART":0,"MN_USG_CD":"02000","MN_USG_CD_NM":"공동주택","ETC_USG":"아파트,판매시설,근린생활시설"},{"PLOT_PSTN":"서울특별시 노원구 중계동 440-3번지","BDAR":109.8,"GFA":173.55,"FART_CMPTTN_GFA":109.8,"FART":0,"MN_USG_CD":"01000","MN_USG_CD_NM":"단독주택","ETC_USG":"주택,점포"},{"PLOT_PSTN":"서울특별시 노원구 중계동 445번지","BDAR":5845.45,"GFA":109964.35,"FART_CMPTTN_GFA":82752.89,"FART":384.89,"MN_USG_CD":"02000","MN_USG_CD_NM":"공동주택","ETC_USG":"공동주택(아파트),상가,유치원,보육시설"},{"PLOT_PSTN":"서울특별시 노원구 중계동 449-2번지","BDAR":2970.45,"GFA":8782.99,"FART_CMPTTN_GFA":8782.99,"FART":82.76,"MN_USG_CD":"10000","MN_USG_CD_NM":"교육연구시설","ETC_USG":"교육연구시설"},{"PLOT_PSTN":"서울특별시 노원구 중계동 502번지","BDAR":2447.07,"GFA":7779.34,"FART_CMPTTN_GFA":7690.54,"FART":64.01,"MN_USG_CD":"10000","MN_USG_CD_NM":"교육연구시설","ETC_USG":"교육연구시설"},{"PLOT_PSTN":"서울특별시 노원구 중계동 502-1번지","BDAR":4555.17,"GFA":57220.54,"FART_CMPTTN_GFA":51936.58,"FART":0,"MN_USG_CD":"02000","MN_USG_CD_NM":"공동주택","ETC_USG":"공동주택(아파트)"},{"PLOT_PSTN":"서울특별시 노원구 중계동 503번지","BDAR":9900.92,"GFA":117492.28,"FART_CMPTTN_GFA":97897.31,"FART":0,"MN_USG_CD":"02000","MN_USG_CD_NM":"공동주택","ETC_USG":"공동주택(아파트),상가,노유자시설"},{"PLOT_PSTN":"서울특별시 노원구 중계동 504번지","BDAR":3430.23,"GFA":15369.13,"FART_CMPTTN_GFA":14283.35,"FART":104.8,"MN_USG_CD":"Z8000","MN_USG_CD_NM":"교육연구및복지시설","ETC_USG":"교육연구및복지시설"},{"PLOT_PSTN":"서울특별시 노원구 중계동 504-1번지","BDAR":4959.03,"GFA":68856.51,"FART_CMPTTN_GFA":64446.25,"FART":0,"MN_USG_CD":"02000","MN_USG_CD_NM":"공동주택","ETC_USG":"공동주택(아파트),판매시설,근린생활시설"},{"PLOT_PSTN":"서울특별시 노원구 중계동 505번지","BDAR":13166.17,"GFA":184059.96,"FART_CMPTTN_GFA":170096.96,"FART":0,"MN_USG_CD":"02000","MN_USG_CD_NM":"공동주택","ETC_USG":"아파트,판매시설,근린생활시설,유치원"},{"PLOT_PSTN":"서울특별시 노원구 중계동 507-3번지","BDAR":0,"GFA":4193.22,"FART_CMPTTN_GFA":0,"FART":0,"MN_USG_CD":"Z5000","MN_USG_CD_NM":"문화및집회시설","ETC_USG":"공공시설(구민회관),제1종근린생활시설,화장실"},{"PLOT_PSTN":"서울특별시 노원구 중계동 508번지","BDAR":3851.75,"GFA":21374.39,"FART_CMPTTN_GFA":8466.51,"FART":35.65,"MN_USG_CD":"Z8000","MN_USG_CD_NM":"교육연구및복지시설","ETC_USG":"문화및집회시설,도서관,팔각정,화장실"},{"PLOT_PSTN":"서울특별시 노원구 중계동 510-1번지","BDAR":2920.31,"GFA":8503.5,"FART_CMPTTN_GFA":8414.7,"FART":75.03,"MN_USG_CD":"10000","MN_USG_CD_NM":"교육연구시설","ETC_USG":"교육연구시설"},{"PLOT_PSTN":"서울특별시 노원구 중계동 510-2번지","BDAR":467.96,"GFA":2565.52,"FART_CMPTTN_GFA":1779.22,"FART":177.92,"MN_USG_CD":"02000","MN_USG_CD_NM":"공동주택","ETC_USG":"연립주택"},{"PLOT_PSTN":"서울특별시 노원구 중계동 511-2번지","BDAR":0,"GFA":134588.12,"FART_CMPTTN_GFA":0,"FART":0,"MN_USG_CD":"02000","MN_USG_CD_NM":"공동주택","ETC_USG":"아파트,상가,공장,탁아소,유치원"},{"PLOT_PSTN":"서울특별시 노원구 중계동 511-3번지","BDAR":2866.44,"GFA":9782.77,"FART_CMPTTN_GFA":9534.13,"FART":81.7,"MN_USG_CD":"Z8000","MN_USG_CD_NM":"교육연구및복지시설","ETC_USG":"교육연구시설"},{"PLOT_PSTN":"서울특별시 노원구 중계동 512번지","BDAR":9757.51,"GFA":113575.35,"FART_CMPTTN_GFA":102701.63,"FART":0,"MN_USG_CD":"02000","MN_USG_CD_NM":"공동주택","ETC_USG":"아파트,상가"},{"PLOT_PSTN":"서울특별시 노원구 중계동 513번지","BDAR":4174.27,"GFA":58022.12,"FART_CMPTTN_GFA":54348.99,"FART":0,"MN_USG_CD":"02000","MN_USG_CD_NM":"공동주택","ETC_USG":"아파트"},{"PLOT_PSTN":"서울특별시 노원구 중계동 513-1번지","BDAR":2368.07,"GFA":7414.8,"FART_CMPTTN_GFA":7326,"FART":60.66,"MN_USG_CD":"10000","MN_USG_CD_NM":"교육연구시설","ETC_USG":"교육연구시설"},{"PLOT_PSTN":"서울특별시 노원구 중계동 514번지","BDAR":3977.0125,"GFA":35438.1764,"FART_CMPTTN_GFA":26219.3826,"FART":214.88,"MN_USG_CD":"02000","MN_USG_CD_NM":"공동주택","ETC_USG":"공동주택(아파트)"},{"PLOT_PSTN":"서울특별시 노원구 중계동 514-2번지","BDAR":4250.87,"GFA":15801.95,"FART_CMPTTN_GFA":14777.3,"FART":83.39,"MN_USG_CD":"Z8000","MN_USG_CD_NM":"교육연구및복지시설","ETC_USG":"교육연구시설"},{"PLOT_PSTN":"서울특별시 노원구 중계동 514-3번지","BDAR":0,"GFA":125594.32,"FART_CMPTTN_GFA":0,"FART":0,"MN_USG_CD":"02000","MN_USG_CD_NM":"공동주택","ETC_USG":"아파트,상가"},{"PLOT_PSTN":"서울특별시 노원구 중계동 515번지","BDAR":5548.93,"GFA":23257.08,"FART_CMPTTN_GFA":18358.67,"FART":96.88,"MN_USG_CD":"10000","MN_USG_CD_NM":"교육연구시설","ETC_USG":"교육연구시설"},{"PLOT_PSTN":"서울특별시 노원구 중계동 515-2번지","BDAR":5040.15,"GFA":73388.89,"FART_CMPTTN_GFA":67898.04,"FART":0,"MN_USG_CD":"02000","MN_USG_CD_NM":"공동주택","ETC_USG":"아파트"},{"PLOT_PSTN":"서울특별시 노원구 중계동 515-3번지","BDAR":2589.06,"GFA":35598.18,"FART_CMPTTN_GFA":33253.29,"FART":137.32,"MN_USG_CD":"02000","MN_USG_CD_NM":"공동주택","ETC_USG":"아파트,판매시설,근린생활시설"},{"PLOT_PSTN":"서울특별시 노원구 중계동 515-5번지","BDAR":713.3,"GFA":991.11,"FART_CMPTTN_GFA":845.26,"FART":35.66,"MN_USG_CD":"19000","MN_USG_CD_NM":"위험물저장및처리시설","ETC_USG":"위험물저장및처리시설"},{"PLOT_PSTN":"서울특별시 노원구 중계동 517번지","BDAR":9675.64,"GFA":39044.53,"FART_CMPTTN_GFA":17656.01,"FART":66.741045,"MN_USG_CD":"07000","MN_USG_CD_NM":"판매시설","ETC_USG":null},{"PLOT_PSTN":"서울특별시 노원구 중계동 576번지","BDAR":1259,"GFA":14399.69,"FART_CMPTTN_GFA":12024.27,"FART":172.95,"MN_USG_CD":"02000","MN_USG_CD_NM":"공동주택","ETC_USG":"아파트"},{"PLOT_PSTN":"서울특별시 노원구 중계동 577번지","BDAR":2497.71,"GFA":21808.54,"FART_CMPTTN_GFA":18931.42,"FART":198.52,"MN_USG_CD":"02000","MN_USG_CD_NM":"공동주택","ETC_USG":"아파트,구매시설,생활시설,의료시설"},{"PLOT_PSTN":"서울특별시 노원구 중계동 578번지","BDAR":1886.15,"GFA":15240.82,"FART_CMPTTN_GFA":13714.12,"FART":173.21,"MN_USG_CD":"02000","MN_USG_CD_NM":"공동주택","ETC_USG":"아파트,생활시설,의료시설"},{"PLOT_PSTN":"서울특별시 노원구 중계동 580번지","BDAR":3105.94,"GFA":50236.22,"FART_CMPTTN_GFA":40388.39,"FART":368.95493,"MN_USG_CD":"02000","MN_USG_CD_NM":"공동주택","ETC_USG":"공동주택(아파트),부대복리시설"},{"PLOT_PSTN":"서울특별시 노원구 중계동 581번지","BDAR":1524.91,"GFA":20279.81,"FART_CMPTTN_GFA":16303.85,"FART":376.21,"MN_USG_CD":"02000","MN_USG_CD_NM":"공동주택","ETC_USG":"아파트,근린생활시설"},{"PLOT_PSTN":"서울특별시 노원구 중계동 582번지","BDAR":2703.365,"GFA":25142.041,"FART_CMPTTN_GFA":18983.039,"FART":169.19,"MN_USG_CD":"02000","MN_USG_CD_NM":"공동주택","ETC_USG":"공동주택(아파트)"},{"PLOT_PSTN":"서울특별시 노원구 중계동 583번지","BDAR":3343.95,"GFA":46267.69,"FART_CMPTTN_GFA":37264.56,"FART":355.99,"MN_USG_CD":"02000","MN_USG_CD_NM":"공동주택","ETC_USG":"공동주택(아파트)"},{"PLOT_PSTN":"서울특별시 노원구 중계동 585번지","BDAR":1568.85,"GFA":22882.93,"FART_CMPTTN_GFA":19437.02,"FART":320.81,"MN_USG_CD":"02000","MN_USG_CD_NM":"공동주택","ETC_USG":"공동주택(아파트), 생활편익시설"},{"PLOT_PSTN":"서울특별시 노원구 중계동 587번지","BDAR":4498.07,"GFA":70709.55,"FART_CMPTTN_GFA":57424.36,"FART":328.38,"MN_USG_CD":"02000","MN_USG_CD_NM":"공동주택","ETC_USG":"공동주택"},{"PLOT_PSTN":"서울특별시 노원구 중계동 587-1번지","BDAR":1361.23,"GFA":26470.95,"FART_CMPTTN_GFA":20874.41,"FART":362.65,"MN_USG_CD":"02000","MN_USG_CD_NM":"공동주택","ETC_USG":"공동주택"},{"PLOT_PSTN":"서울특별시 노원구 중계동 588번지","BDAR":4941.08,"GFA":92344.54,"FART_CMPTTN_GFA":68148.12,"FART":331.46,"MN_USG_CD":"02000","MN_USG_CD_NM":"공동주택","ETC_USG":"아파트(공동주택), 생활편익시설"},{"PLOT_PSTN":"서울특별시 노원구 중계동 588-1번지","BDAR":1073,"GFA":16063.87,"FART_CMPTTN_GFA":14408.53,"FART":0,"MN_USG_CD":"02000","MN_USG_CD_NM":"공동주택","ETC_USG":"아파트"},{"PLOT_PSTN":"서울특별시 노원구 중계동 590번지","BDAR":1950.001,"GFA":32078.819,"FART_CMPTTN_GFA":23751.4,"FART":278.69,"MN_USG_CD":"02000","MN_USG_CD_NM":"공동주택","ETC_USG":"공동주택(아파트), 생활편익시설"},{"PLOT_PSTN":"서울특별시 노원구 중계동 592번지","BDAR":1979.149,"GFA":35289.725,"FART_CMPTTN_GFA":25791.385,"FART":375.39,"MN_USG_CD":"02000","MN_USG_CD_NM":"공동주택","ETC_USG":"공동주택(아파트), 생활편익시설"},{"PLOT_PSTN":"서울특별시 노원구 중계동 593번지","BDAR":4439.32,"GFA":68644.62,"FART_CMPTTN_GFA":48539.5,"FART":307.83,"MN_USG_CD":"02000","MN_USG_CD_NM":"공동주택","ETC_USG":"아파트(공동주택),생활편익시설"},{"PLOT_PSTN":"서울특별시 노원구 중계동 597번지","BDAR":2293.0956,"GFA":42752.1262,"FART_CMPTTN_GFA":31892.4562,"FART":357.35,"MN_USG_CD":"02000","MN_USG_CD_NM":"공동주택","ETC_USG":"공동주택(아파트)"},{"PLOT_PSTN":"서울특별시 노원구 중계동 598번지","BDAR":4545.098,"GFA":63237.092,"FART_CMPTTN_GFA":49679.472,"FART":242.09,"MN_USG_CD":"02000","MN_USG_CD_NM":"공동주택","ETC_USG":"공동주택(아파트)"},{"PLOT_PSTN":"서울특별시 노원구 중계동 599번지","BDAR":1151.82,"GFA":12772.05,"FART_CMPTTN_GFA":9958.09,"FART":239.95,"MN_USG_CD":"02000","MN_USG_CD_NM":"공동주택","ETC_USG":"아파트"},{"PLOT_PSTN":"서울특별시 노원구 중계동 600번지","BDAR":511.32,"GFA":6539.91,"FART_CMPTTN_GFA":5413.69,"FART":299.56,"MN_USG_CD":"02000","MN_USG_CD_NM":"공동주택","ETC_USG":"아파트"},{"PLOT_PSTN":"서울특별시 노원구 중계동 601번지","BDAR":1966.27,"GFA":14715.991,"FART_CMPTTN_GFA":10897.006,"FART":200,"MN_USG_CD":"02000","MN_USG_CD_NM":"공동주택","ETC_USG":"공동주택(아파트)"},{"PLOT_PSTN":"서울특별시 노원구 중계동 602번지","BDAR":765.327,"GFA":11889.381,"FART_CMPTTN_GFA":8567.1,"FART":285.57,"MN_USG_CD":"02000","MN_USG_CD_NM":"공동주택","ETC_USG":"공동주택"},{"PLOT_PSTN":"서울특별시 노원구 중계동 606번지","BDAR":2602.9,"GFA":49962.509,"FART_CMPTTN_GFA":34494.454,"FART":270.88,"MN_USG_CD":"02000","MN_USG_CD_NM":"공동주택","ETC_USG":"아파트"},{"PLOT_PSTN":"서울특별시 노원구 중계동 산26번지","BDAR":184.01,"GFA":239.69,"FART_CMPTTN_GFA":99.53,"FART":0,"MN_USG_CD":"27000","MN_USG_CD_NM":"관광휴게시설","ETC_USG":"공원관리사무실,화장실"},{"PLOT_PSTN":"서울특별시 노원구 중계동 산42-3번지","BDAR":1286.76,"GFA":1572.95,"FART_CMPTTN_GFA":1572.95,"FART":17.68,"MN_USG_CD":"05000","MN_USG_CD_NM":"문화및집회시설","ETC_USG":"문화및집회시설"},{"PLOT_PSTN":"서울특별시 노원구 중계동 산95-2번지","BDAR":488.51,"GFA":488.51,"FART_CMPTTN_GFA":488.51,"FART":7.94,"MN_USG_CD":"03000","MN_USG_CD_NM":"제1종근린생활시설","ETC_USG":"제1종근린생활시설(마을공동시설)"},{"PLOT_PSTN":"서울특별시 노원구 중계동 산104-11번지","BDAR":70.5,"GFA":70.5,"FART_CMPTTN_GFA":70.5,"FART":0,"MN_USG_CD":"01000","MN_USG_CD_NM":"단독주택","ETC_USG":"주택"}]}